{
	"id": "mig_cmnesb642iih018ki08g",
	"parentID": "mig_cmis2jrvv9jpetvg3dng",
	"checksum": "1:ecc3c32a0988e41c9f2b44f59824c9a9c5d59022a810724ac3072098d907c441",
	"operations": [
		{
			"addTable": {
				"table": "frequently_asked_questions_categories"
			}
		},
		{
			"addColumn": {
				"column": {
					"name": "name",
					"type": "string"
				},
				"table": "frequently_asked_questions_categories"
			}
		},
		{
			"addColumn": {
				"column": {
					"name": "xatacreatedAt",
					"type": "string"
				},
				"table": "frequently_asked_questions_categories"
			}
		},
		{
			"addColumn": {
				"column": {
					"name": "xataupdatedAt",
					"type": "string"
				},
				"table": "frequently_asked_questions_categories"
			}
		},
		{
			"addColumn": {
				"column": {
					"name": "xataversion",
					"type": "int"
				},
				"table": "frequently_asked_questions_categories"
			}
		}
	]
}
